LICENSE
MANIFEST.in
README.md
requirements.txt
setup.cfg
setup.py
src/robotframework_salabsutils.egg-info/PKG-INFO
src/robotframework_salabsutils.egg-info/SOURCES.txt
src/robotframework_salabsutils.egg-info/dependency_links.txt
src/robotframework_salabsutils.egg-info/requires.txt
src/robotframework_salabsutils.egg-info/top_level.txt
src/salabsutils/__init__.py
src/salabsutils/base_class.py
src/salabsutils/utils.py
src/salabsutils/version.py